paperboy/__init__.py
paperboy/engine.py
paperboy/handler.py
paperboy/helpers.py
paperboy/logs.py
paperboy/stores/__init__.py
paperboy/stores/base.py
paperboy/stores/memory.py
paperboy/stores/rocksdb.py
paperboy/stores/types.py
paperboy/table.py
kafka_paperboy-0.4.1.dist-info/METADATA
kafka_paperboy-0.4.1.dist-info/WHEEL
kafka_paperboy-0.4.1.dist-info/RECORD
