Metadata-Version: 2.1
Name: kafka-paperboy
Version: 0.4.1
Summary: Kafka ingester for python built around aiokafka
Author: Franck Lourme
Author-email: coton@42.fr
Requires-Python: >=3.11,<4.0
Classifier: Programming Language :: Python :: 3
Classifier: Programming Language :: Python :: 3.11
Requires-Dist: aiokafka (>=0.8.1,<0.9.0)
Requires-Dist: msgpack (>=1.0.7,<2.0.0)
Requires-Dist: python-schema-registry-client (>=2.5.0,<3.0.0)
Requires-Dist: rocksdict (>=0.3.18,<0.4.0)
